<?xml version="1.0" ?>
<Scene.XML>
<!--r3d Scene-->
<Objects>
 <bk_bunker_metal_001_2 file="bk_bunker_metal_001_2.msh" />
 <bk_bunker_metal_001_p1 file="bk_bunker_metal_001_p1.msh" />
 <bk_bunker_metal_001_p2 file="bk_bunker_metal_001_p2.msh" />
 <bk_bunker_metal_001_p3 file="bk_bunker_metal_001_p3.msh" />
 <bk_bunker_metal_001_p4 file="bk_bunker_metal_001_p4.msh" />
 <bk_bunker_metal_001_p5 file="bk_bunker_metal_001_p5.msh" />
 <bk_bunker_metal_001_p6 file="bk_bunker_metal_001_p6.msh" />
 <bk_bunker_metal_001_p7 file="bk_bunker_metal_001_p7.msh" />
</Objects>
<Materials version="2">
  <mbk_bunker_metal_001_2_id01
    diffuse="bk_bunker_metal_001_01_d.dds"
    color="255 255 255"
  />
  <mbk_bunker_metal_001_2_id02
    diffuse="bk_bunker_metal_001_02_d.dds"
    color="255 255 255"
  />
  <mbk_bunker_metal_001_2_id03
    diffuse="bk_bunker_metal_001_03_d.dds"
    color="255 255 255"
  />
  <mbk_bunker_metal_001_2_id04
    diffuse="bk_bunker_metal_001_04_d.dds"
    color="255 255 255"
  />
  <mEmptyMat
  />
</Materials>
<Skeleton
  file="bk_bunker_metal_001_2.skl"
/>
<BoneAnim
  file="Anims\bk_bunker_metal_001_2.anm"
/>
<collision
  file="bk_bunker_metal_001_2.col"
/>
</Scene.XML>
