<?xml version="1.0" encoding="UTF-8"?>
<SPAWN.XML>
	<spawn type="monster_spawn" engName="pancakefx" code="20971521" teamId="0" spawnId="0" posX="70" posY="-2" posZ="9" angleY="180" scale="1" radius="1" respawnTime="1" msgId="npc0001"/>
	<spawn type="monster_spawn" engName="pancakefx" code="20971521" teamId="0" spawnId="1" posX="35" posY="-2" posZ="-7" angleY="180" scale="1" radius="1" respawnTime="1" msgId="npc0001"/>
	<spawn type="monster_spawn" engName="pancakefx" code="20971521" teamId="0" spawnId="2" posX="46" posY="-2" posZ="39" angleY="180" scale="1" radius="1" respawnTime="1" msgId="npc0001"/>
	<spawn type="monster_spawn" engName="pancakefx" code="20971521" teamId="0" spawnId="3" posX="101" posY="-2" posZ="-58" angleY="180" scale="1" radius="1" respawnTime="1" msgId="npc0001"/>
	<spawn type="monster_spawn" engName="pancakefx" code="20971521" teamId="0" spawnId="4" posX="87" posY="-2" posZ="-73" angleY="180" scale="1" radius="1" respawnTime="1" msgId="npc0001"/>
	<spawn type="monster_spawn" engName="pancakefx" code="20971521" teamId="0" spawnId="5" posX="62" posY="-2" posZ="-78" angleY="180" scale="1" radius="1" respawnTime="1" msgId="npc0001"/>
	<spawn type="monster_spawn" engName="pancakefx" code="20971521" teamId="0" spawnId="6" posX="-16" posY="-1" posZ="-55" angleY="180" scale="1" radius="1" respawnTime="1" msgId="npc0001"/>
	<spawn type="monster_spawn" engName="pancakefx" code="20971521" teamId="0" spawnId="7" posX="-26" posY="1" posZ="0" angleY="180" scale="1" radius="1" respawnTime="1" msgId="npc0001"/>
	<spawn type="monster_spawn" engName="pancakefx" code="20971521" teamId="0" spawnId="8" posX="-14.9901" posY="0" posZ="32.0501" angleY="180" scale="1" radius="1" respawnTime="1" msgId="npc0001"/>
	<spawn type="monster_spawn" engName="pancakefx" code="20971521" teamId="0" spawnId="9" posX="12" posY="0" posZ="5" angleY="180" scale="1" radius="1" respawnTime="1" msgId="npc0001"/>
	<spawn type="monster_spawn" engName="pancakefx" code="20971521" teamId="0" spawnId="10" posX="-56" posY="1" posZ="-77" angleY="180" scale="1" radius="1" respawnTime="1" msgId="npc0001"/>
	<spawn type="monster_spawn" engName="pancakefx" code="20971521" teamId="0" spawnId="11" posX="-95" posY="1" posZ="-63" angleY="180" scale="1" radius="1" respawnTime="1" msgId="npc0001"/>
	<spawn type="monster_spawn" engName="pancakefx" code="20971521" teamId="0" spawnId="12" posX="-115" posY="1" posZ="-19" angleY="180" scale="1" radius="1" respawnTime="1" msgId="npc0001"/>
	<spawn type="monster_spawn" engName="pancakefx" code="20971521" teamId="0" spawnId="13" posX="-59" posY="1" posZ="-15" angleY="180" scale="1" radius="1" respawnTime="1" msgId="npc0001"/>
	<spawn type="monster_spawn" engName="pancakefx" code="20971521" teamId="0" spawnId="14" posX="-113" posY="5" posZ="17" angleY="180" scale="1" radius="1" respawnTime="1" msgId="npc0001"/>
	<spawn type="monster_spawn" engName="pancakefx" code="20971521" teamId="0" spawnId="15" posX="-106" posY="5" posZ="39" angleY="180" scale="1" radius="1" respawnTime="1" msgId="npc0001"/>
	<spawn type="monster_spawn" engName="pancakefx" code="20971521" teamId="0" spawnId="16" posX="-68" posY="5" posZ="49" angleY="180" scale="1" radius="1" respawnTime="1" msgId="npc0001"/>
	<spawn type="attackPoint" engName="GiroroCat" code="19922953" teamId="0" spawnId="17" posX="46" posY="-2" posZ="33" angleY="180" scale="1" radius="1" respawnTime="1" msgId="npc0001"/>
	<spawn type="attackPoint" engName="GiroroCat" code="19922953" teamId="0" spawnId="18" posX="42" posY="-3" posZ="17" angleY="180" scale="1" radius="1" respawnTime="1" msgId="npc0001"/>
	<spawn type="attackPoint" engName="GiroroCat" code="19922953" teamId="0" spawnId="19" posX="51" posY="-3" posZ="3" angleY="180" scale="1" radius="1" respawnTime="1" msgId="npc0001"/>
	<spawn type="attackPoint" engName="GiroroCat" code="19922953" teamId="0" spawnId="20" posX="42" posY="-3" posZ="-15" angleY="180" scale="1" radius="1" respawnTime="1" msgId="npc0001"/>
	<spawn type="attackPoint" engName="GiroroCat" code="19922953" teamId="0" spawnId="21" posX="55" posY="-3" posZ="-14" angleY="180" scale="1" radius="1" respawnTime="1" msgId="npc0001"/>
	<spawn type="attackPoint" engName="GiroroCat" code="19922953" teamId="0" spawnId="22" posX="36" posY="-3" posZ="-26" angleY="180" scale="1" radius="1" respawnTime="1" msgId="npc0001"/>
	<spawn type="attackPoint" engName="GiroroCat" code="19922953" teamId="0" spawnId="23" posX="58" posY="-3" posZ="-33" angleY="180" scale="1" radius="1" respawnTime="1" msgId="npc0001"/>
	<spawn type="attackPoint" engName="GiroroCat" code="19922953" teamId="0" spawnId="24" posX="46" posY="-2" posZ="-48" angleY="180" scale="1" radius="1" respawnTime="1" msgId="npc0001"/>
	<spawn type="attackPoint" engName="GiroroCat" code="19922953" teamId="0" spawnId="25" posX="73" posY="-2" posZ="-29" angleY="180" scale="1" radius="1" respawnTime="1" msgId="npc0001"/>
	<spawn type="attackPoint" engName="GiroroCat" code="19922953" teamId="0" spawnId="26" posX="69" posY="-2" posZ="-8" angleY="180" scale="1" radius="1" respawnTime="1" msgId="npc0001"/>
	<spawn type="attackPoint" engName="GiroroCat" code="19922953" teamId="0" spawnId="27" posX="67" posY="-2" posZ="16" angleY="180" scale="1" radius="1" respawnTime="1" msgId="npc0001"/>
	<spawn type="attackPoint" engName="GiroroCat" code="19922953" teamId="0" spawnId="28" posX="41" posY="-2" posZ="-4" angleY="180" scale="1" radius="1" respawnTime="1" msgId="npc0001"/>
	<spawn type="attackPoint" engName="GiroroCat" code="19922953" teamId="0" spawnId="29" posX="47" posY="-3" posZ="-34" angleY="180" scale="1" radius="1" respawnTime="1" msgId="npc0001"/>
	<spawn type="attackPoint" engName="GiroroCat" code="19922953" teamId="0" spawnId="30" posX="-18" posY="0" posZ="27" angleY="180" scale="1" radius="1" respawnTime="1" msgId="npc0001"/>
	<spawn type="attackPoint" engName="GiroroCat" code="19922953" teamId="0" spawnId="31" posX="-23" posY="1" posZ="8" angleY="180" scale="1" radius="1" respawnTime="1" msgId="npc0001"/>
	<spawn type="attackPoint" engName="GiroroCat" code="19922953" teamId="0" spawnId="32" posX="-19" posY="0" posZ="-10" angleY="180" scale="1" radius="1" respawnTime="1" msgId="npc0001"/>
	<spawn type="attackPoint" engName="GiroroCat" code="19922953" teamId="0" spawnId="33" posX="8" posY="-1" posZ="-5" angleY="180" scale="1" radius="1" respawnTime="1" msgId="npc0001"/>
	<spawn type="attackPoint" engName="GiroroCat" code="19922953" teamId="0" spawnId="34" posX="-7" posY="-2" posZ="-28" angleY="180" scale="1" radius="1" respawnTime="1" msgId="npc0001"/>
	<spawn type="attackPoint" engName="GiroroCat" code="19922953" teamId="0" spawnId="35" posX="14" posY="0" posZ="-2" angleY="180" scale="1" radius="1" respawnTime="1" msgId="npc0001"/>
	<spawn type="attackPoint" engName="GiroroCat" code="19922953" teamId="0" spawnId="36" posX="-18" posY="-1" posZ="-49" angleY="180" scale="1" radius="1" respawnTime="1" msgId="npc0001"/>
	<spawn type="attackPoint" engName="GiroroCat" code="19922953" teamId="0" spawnId="37" posX="-54" posY="1" posZ="-50" angleY="180" scale="1" radius="1" respawnTime="1" msgId="npc0001"/>
	<spawn type="attackPoint" engName="GiroroCat" code="19922953" teamId="0" spawnId="38" posX="-50" posY="1" posZ="-34" angleY="180" scale="1" radius="1" respawnTime="1" msgId="npc0001"/>
	<spawn type="attackPoint" engName="GiroroCat" code="19922953" teamId="0" spawnId="39" posX="-53" posY="1" posZ="-14" angleY="180" scale="1" radius="1" respawnTime="1" msgId="npc0001"/>
	<spawn type="attackPoint" engName="GiroroCat" code="19922953" teamId="0" spawnId="40" posX="-70" posY="0" posZ="-9" angleY="180" scale="1" radius="1" respawnTime="1" msgId="npc0001"/>
	<spawn type="attackPoint" engName="GiroroCat" code="19922953" teamId="0" spawnId="41" posX="-81" posY="1" posZ="-13" angleY="180" scale="1" radius="1" respawnTime="1" msgId="npc0001"/>
	<spawn type="attackPoint" engName="GiroroCat" code="19922953" teamId="0" spawnId="42" posX="-86" posY="1" posZ="-24" angleY="180" scale="1" radius="1" respawnTime="1" msgId="npc0001"/>
	<spawn type="attackPoint" engName="GiroroCat" code="19922953" teamId="0" spawnId="43" posX="-92" posY="1" posZ="-34" angleY="180" scale="1" radius="1" respawnTime="1" msgId="npc0001"/>
	<spawn type="attackPoint" engName="GiroroCat" code="19922953" teamId="0" spawnId="44" posX="-78" posY="1" posZ="-44" angleY="180" scale="1" radius="1" respawnTime="1" msgId="npc0001"/>
	<spawn type="attackPoint" engName="GiroroCat" code="19922953" teamId="0" spawnId="45" posX="-70" posY="1" posZ="-34" angleY="180" scale="1" radius="1" respawnTime="1" msgId="npc0001"/>
	<spawn type="attackPoint" engName="GiroroCat" code="19922953" teamId="0" spawnId="46" posX="-85" posY="1" posZ="-55" angleY="180" scale="1" radius="1" respawnTime="1" msgId="npc0001"/>
	<spawn type="attackPoint" engName="GiroroCat" code="19922953" teamId="0" spawnId="47" posX="-108" posY="1" posZ="-19" angleY="180" scale="1" radius="1" respawnTime="1" msgId="npc0001"/>
	<spawn type="attackPoint" engName="GiroroCat" code="19922953" teamId="0" spawnId="48" posX="-49" posY="1" posZ="-62" angleY="180" scale="1" radius="1" respawnTime="1" msgId="npc0001"/>
	<spawn type="attackPoint" engName="GiroroCat" code="19922953" teamId="0" spawnId="49" posX="-82" posY="4" posZ="29" angleY="180" scale="1" radius="1" respawnTime="1" msgId="npc0001"/>
	<spawn type="attackPoint" engName="GiroroCat" code="19922953" teamId="0" spawnId="50" posX="-69" posY="5" posZ="42" angleY="180" scale="1" radius="1" respawnTime="1" msgId="npc0001"/>
	<spawn type="attackPoint" engName="GiroroCat" code="19922953" teamId="0" spawnId="51" posX="-54" posY="4" posZ="30" angleY="180" scale="1" radius="1" respawnTime="1" msgId="npc0001"/>
	<spawn type="attackPoint" engName="GiroroCat" code="19922953" teamId="0" spawnId="52" posX="-66" posY="4" posZ="13" angleY="180" scale="1" radius="1" respawnTime="1" msgId="npc0001"/>
	<spawn type="attackPoint" engName="GiroroCat" code="19922953" teamId="0" spawnId="53" posX="-51" posY="4" posZ="13" angleY="180" scale="1" radius="1" respawnTime="1" msgId="npc0001"/>
	<spawn type="attackPoint" engName="GiroroCat" code="19922953" teamId="0" spawnId="54" posX="-105" posY="5" posZ="14" angleY="180" scale="1" radius="1" respawnTime="1" msgId="npc0001"/>
	<spawn type="attackPoint" engName="GiroroCat" code="19922953" teamId="0" spawnId="55" posX="-103" posY="5" posZ="27" angleY="180" scale="1" radius="1" respawnTime="1" msgId="npc0001"/>
	<spawn type="coopZone" engName="Keroro" code="18939905" teamId="0" spawnId="1" posX="69.2702" posY="-3" posZ="38.5299" angleY="180" scale="1" radius="1.7" respawnTime="1" msgId="npc0001"/>
	<spawn type="triggerPoint" engName="triggerPoint_001" code="201719809" teamId="0" spawnId="57" posX="49" posY="-3" posZ="13" angleY="180" scale="1" radius="15" respawnTime="1" msgId="npc0001"/>
	<spawn type="triggerPoint" engName="triggerPoint_002" code="201719810" teamId="0" spawnId="58" posX="25" posY="-2.54" posZ="-24" angleY="180" scale="1" radius="4" respawnTime="1" msgId="npc0001"/>
	<spawn type="triggerPoint" engName="triggerPoint_003" code="201719811" teamId="0" spawnId="59" posX="-26" posY="-1.91" posZ="-21" angleY="180" scale="1" radius="5" respawnTime="1" msgId="npc0001"/>
	<spawn type="triggerPoint" engName="triggerPoint_004" code="201719812" teamId="0" spawnId="60" posX="-88.6" posY="1.24" posZ="-2.8" angleY="350.8" scale="1" radius="4" respawnTime="1" msgId="npc0001"/>
	<spawn type="triggerPoint" engName="triggerPoint_005" code="201719813" teamId="0" spawnId="61" posX="-91.0202" posY="3.53" posZ="2" angleY="180" scale="1" radius="3" respawnTime="1" msgId="npc0001"/>
	<spawn type="attackPoint" engName="GiroroCat" code="19922953" teamId="0" spawnId="62" posX="-4" posY="-2" posZ="-38" angleY="180" scale="1" radius="1" respawnTime="1" msgId="npc0001"/>
	<spawn type="attackPoint" engName="GiroroCat" code="19922953" teamId="0" spawnId="63" posX="-16" posY="-2" posZ="-32" angleY="180" scale="1" radius="1" respawnTime="1" msgId="npc0001"/>
	<spawn type="attackPoint" engName="GiroroCat" code="19922953" teamId="0" spawnId="64" posX="10" posY="-2" posZ="-21" angleY="180" scale="1" radius="1" respawnTime="1" msgId="npc0001"/>
	<spawn type="attackPoint" engName="GiroroCat" code="19922953" teamId="0" spawnId="65" posX="-17" posY="0" posZ="-7" angleY="180" scale="1" radius="1" respawnTime="1" msgId="npc0001"/>
	<spawn type="attackPoint" engName="GiroroCat" code="19922953" teamId="0" spawnId="66" posX="-15" posY="-2" posZ="-17" angleY="180" scale="1" radius="1" respawnTime="1" msgId="npc0001"/>
	<spawn type="attackPoint" engName="GiroroCat" code="19922953" teamId="0" spawnId="67" posX="-5" posY="-1" posZ="0" angleY="180" scale="1" radius="1" respawnTime="1" msgId="npc0001"/>
	<spawn type="attackPoint" engName="GiroroCat" code="19922953" teamId="0" spawnId="68" posX="-15" posY="0" posZ="4" angleY="180" scale="1" radius="1" respawnTime="1" msgId="npc0001"/>
	<spawn type="attackPoint" engName="GiroroCat" code="19922953" teamId="0" spawnId="69" posX="-6" posY="-1" posZ="14" angleY="180" scale="1" radius="1" respawnTime="1" msgId="npc0001"/>
	<spawn type="attackPoint" engName="GiroroCat" code="19922953" teamId="0" spawnId="70" posX="-5" posY="-1" posZ="23" angleY="180" scale="1" radius="1" respawnTime="1" msgId="npc0001"/>
	<spawn type="attackPoint" engName="GiroroCat" code="19922953" teamId="0" spawnId="71" posX="6" posY="-1" posZ="16" angleY="180" scale="1" radius="1" respawnTime="1" msgId="npc0001"/>
	<spawn type="attackPoint" engName="GiroroCat" code="19922953" teamId="0" spawnId="72" posX="3" posY="-1" posZ="4" angleY="180" scale="1" radius="1" respawnTime="1" msgId="npc0001"/>
	<spawn type="attackPoint" engName="GiroroCat" code="19922953" teamId="0" spawnId="73" posX="10" posY="0" posZ="6" angleY="180" scale="1" radius="1" respawnTime="1" msgId="npc0001"/>
	<spawn type="attackPoint" engName="GiroroCat" code="19922953" teamId="0" spawnId="74" posX="18" posY="-1" posZ="-10" angleY="180" scale="1" radius="1" respawnTime="1" msgId="npc0001"/>
	<spawn type="monster_spawn" engName="octopus" code="20971523" teamId="0" spawnId="75" posX="56" posY="-2.58" posZ="-23" angleY="180" scale="1" radius="1" respawnTime="1" msgId="npc0001"/>
	<spawn type="monster_spawn" engName="octopus" code="20971523" teamId="0" spawnId="76" posX="51" posY="-2.6" posZ="-35" angleY="180" scale="1" radius="1" respawnTime="1" msgId="npc0001"/>
	<spawn type="monster_spawn" engName="octopus" code="20971523" teamId="0" spawnId="77" posX="44" posY="-2.59" posZ="-35" angleY="180" scale="1" radius="1" respawnTime="1" msgId="npc0001"/>
	<spawn type="monster_spawn" engName="octopus" code="20971523" teamId="0" spawnId="78" posX="71.7503" posY="-2.19" posZ="-36.99" angleY="180" scale="1" radius="1" respawnTime="1" msgId="npc0001"/>
	<spawn type="monster_spawn" engName="octopus" code="20971523" teamId="0" spawnId="79" posX="62" posY="-2.23" posZ="-45" angleY="180" scale="1" radius="1" respawnTime="1" msgId="npc0001"/>
	<spawn type="monster_spawn" engName="octopus" code="20971523" teamId="0" spawnId="80" posX="44" posY="-2.19" posZ="-50" angleY="180" scale="1" radius="1" respawnTime="1" msgId="npc0001"/>
	<spawn type="monster_spawn" engName="octopus" code="20971523" teamId="0" spawnId="81" posX="-1" posY="0" posZ="-11" angleY="180" scale="1" radius="1" respawnTime="1" msgId="npc0001"/>
	<spawn type="monster_spawn" engName="octopus" code="20971523" teamId="0" spawnId="82" posX="-23" posY="1" posZ="15" angleY="180" scale="1" radius="1" respawnTime="1" msgId="npc0001"/>
	<spawn type="monster_spawn" engName="octopus" code="20971523" teamId="0" spawnId="83" posX="-14" posY="0" posZ="29" angleY="180" scale="1" radius="1" respawnTime="1" msgId="npc0001"/>
	<spawn type="monster_spawn" engName="octopus" code="20971523" teamId="0" spawnId="84" posX="10" posY="0" posZ="26" angleY="180" scale="1" radius="1" respawnTime="1" msgId="npc0001"/>
	<spawn type="monster_spawn" engName="octopus" code="20971523" teamId="0" spawnId="85" posX="-10" posY="-1" posZ="-53" angleY="180" scale="1" radius="1" respawnTime="1" msgId="npc0001"/>
	<spawn type="monster_spawn" engName="octopus" code="20971523" teamId="0" spawnId="86" posX="-5" posY="-1" posZ="-15" angleY="180" scale="1" radius="1" respawnTime="1" msgId="npc0001"/>
	<spawn type="monster_spawn" engName="octopus" code="20971523" teamId="0" spawnId="87" posX="-5" posY="-0.789999" posZ="-7" angleY="180" scale="1" radius="1" respawnTime="1" msgId="npc0001"/>
	<spawn type="monster_spawn" engName="octopus" code="20971523" teamId="0" spawnId="88" posX="0" posY="-0.4" posZ="-5" angleY="180" scale="1" radius="1" respawnTime="1" msgId="npc0001"/>
	<spawn type="monster_spawn" engName="octopus" code="20971523" teamId="0" spawnId="89" posX="4" posY="-1" posZ="-13" angleY="180" scale="1" radius="1" respawnTime="1" msgId="npc0001"/>
	<spawn type="triggerPoint" engName="triggerPoint_006" code="201719814" teamId="0" spawnId="90" posX="-80" posY="0.42" posZ="-19.24" angleY="180" scale="1" radius="16" respawnTime="1" msgId="npc0001"/>
	<spawn type="monster_spawn" engName="octopus" code="20971523" teamId="0" spawnId="91" posX="-72" posY="1" posZ="-35" angleY="180" scale="1" radius="1" respawnTime="1" msgId="npc0001"/>
	<spawn type="monster_spawn" engName="octopus" code="20971523" teamId="0" spawnId="92" posX="-90" posY="1" posZ="-19" angleY="180" scale="1" radius="1" respawnTime="1" msgId="npc0001"/>
	<spawn type="monster_spawn" engName="octopus" code="20971523" teamId="0" spawnId="93" posX="-84.1305" posY="1" posZ="-12" angleY="180" scale="1" radius="1" respawnTime="1" msgId="npc0001"/>
	<spawn type="monster_spawn" engName="octopus" code="20971523" teamId="0" spawnId="94" posX="-52" posY="1" posZ="-36" angleY="180" scale="1" radius="1" respawnTime="1" msgId="npc0001"/>
	<spawn type="monster_spawn" engName="octopus" code="20971523" teamId="0" spawnId="95" posX="-61" posY="1" posZ="-27" angleY="180" scale="1" radius="1" respawnTime="1" msgId="npc0001"/>
	<spawn type="monster_spawn" engName="octopus" code="20971523" teamId="0" spawnId="96" posX="-57.9" posY="1.2" posZ="-16.67" angleY="180" scale="1" radius="1" respawnTime="1" msgId="npc0001"/>
	<spawn type="monster_spawn" engName="octopus" code="20971523" teamId="0" spawnId="97" posX="-36.5801" posY="1" posZ="-23.26" angleY="180" scale="1" radius="1" respawnTime="1" msgId="npc0001"/>
	<spawn type="monster_spawn" engName="octopus" code="20971523" teamId="0" spawnId="98" posX="-99.96" posY="5" posZ="21.2401" angleY="180" scale="1" radius="1" respawnTime="1" msgId="npc0001"/>
	<spawn type="monster_spawn" engName="octopus" code="20971523" teamId="0" spawnId="99" posX="-90" posY="5" posZ="41" angleY="180" scale="1" radius="1" respawnTime="1" msgId="npc0001"/>
	<spawn type="monster_spawn" engName="octopus" code="20971523" teamId="0" spawnId="100" posX="-58" posY="5" posZ="43" angleY="180" scale="1" radius="1" respawnTime="1" msgId="npc0001"/>
	<spawn type="monster_spawn" engName="octopus" code="20971523" teamId="0" spawnId="101" posX="-40.3201" posY="5" posZ="31.96" angleY="180" scale="1" radius="1" respawnTime="1" msgId="npc0001"/>
	<spawn type="monster_spawn" engName="octopus" code="20971523" teamId="0" spawnId="102" posX="-76.0897" posY="5" posZ="11" angleY="180" scale="1" radius="1" respawnTime="1" msgId="npc0001"/>
	<spawn type="triggerPoint" engName="triggerPoint_007" code="201719815" teamId="0" spawnId="103" posX="49" posY="-3" posZ="-26" angleY="180" scale="1" radius="1" respawnTime="1" msgId="npc0001"/>
	<spawn type="triggerPoint" engName="triggerPoint_008" code="201719816" teamId="0" spawnId="104" posX="-1" posY="0" posZ="-8" angleY="180" scale="1" radius="1" respawnTime="1" msgId="npc0001"/>
	<spawn type="triggerPoint" engName="triggerPoint_009" code="201719817" teamId="0" spawnId="105" posX="-64" posY="1" posZ="-27" angleY="180" scale="1" radius="1" respawnTime="1" msgId="npc0001"/>
	<spawn type="triggerPoint" engName="triggerPoint_010" code="201719818" teamId="0" spawnId="106" posX="39" posY="-3" posZ="-25.1499" angleY="180" scale="1" radius="10" respawnTime="1" msgId="npc0001"/>
	<spawn type="triggerPoint" engName="triggerPoint_011" code="201719819" teamId="0" spawnId="107" posX="-3.81999" posY="-1" posZ="-19" angleY="180" scale="1" radius="15" respawnTime="1" msgId="npc0001"/>
	
	<spawn type="itembox" engName="reinforce_8" code="155189256" teamId="0" spawnId="108" posX="-89" posY="4.37999" posZ="25" angleY="180" scale="1" radius="1" respawnTime="60" msgId="npc0001"/>
	<spawn type="itembox" engName="restoration_9" code="154140681" teamId="0" spawnId="109" posX="-55" posY="4.37999" posZ="4" angleY="180" scale="1" radius="1" respawnTime="40" msgId="npc0001"/>
	<spawn type="itembox" engName="restoration_9" code="154140681" teamId="0" spawnId="110" posX="-52" posY="4.35999" posZ="29" angleY="180" scale="1" radius="1" respawnTime="40" msgId="npc0001"/>
	<spawn type="itembox" engName="reinforce_9" code="155189257" teamId="0" spawnId="111" posX="-42" posY="4.35999" posZ="18" angleY="180" scale="1" radius="1" respawnTime="40" msgId="npc0001"/>
	<spawn type="itembox" engName="restoration_9" code="154140681" teamId="0" spawnId="112" posX="-7" posY="-0.619999" posZ="18" angleY="180" scale="1" radius="1" respawnTime="40" msgId="npc0001"/>
	<spawn type="itembox" engName="reinforce_9" code="155189257" teamId="0" spawnId="113" posX="2" posY="-0.659999" posZ="18" angleY="180" scale="1" radius="1" respawnTime="40" msgId="npc0001"/>	
	
</SPAWN.XML>