<?xml version="1.0" encoding="UTF-8"?>
<SPAWN.XML>
	<spawn type="privateZone" engName="Keroro" code="18939905" teamId="0" spawnId="0" posX="-23.5" posY="2" posZ="-24" angleY="180" scale="1" radius="1" respawnTime="1" msgId="npc0001"/>
	<spawn type="privateZone" engName="Keroro" code="18939905" teamId="0" spawnId="1" posX="-3" posY="0.5" posZ="-27" angleY="180" scale="1" radius="1" respawnTime="1" msgId="npc0001"/>
	<spawn type="privateZone" engName="Keroro" code="18939905" teamId="0" spawnId="2" posX="-23" posY="2" posZ="-10" angleY="180" scale="1" radius="1" respawnTime="1" msgId="npc0001"/>
	<spawn type="privateZone" engName="Keroro" code="18939905" teamId="0" spawnId="3" posX="-27" posY="0.5" posZ="13" angleY="180" scale="1" radius="1" respawnTime="1" msgId="npc0001"/>
	<spawn type="privateZone" engName="Keroro" code="18939905" teamId="0" spawnId="4" posX="-23" posY="2" posZ="19" angleY="180" scale="1" radius="1" respawnTime="1" msgId="npc0001"/>
	<spawn type="privateZone" engName="Tamama" code="19005441" teamId="1" spawnId="5" posX="23" posY="2" posZ="24" angleY="180" scale="1" radius="1" respawnTime="1" msgId="npc0001"/>
	<spawn type="privateZone" engName="Tamama" code="19005441" teamId="1" spawnId="6" posX="3" posY="0.5" posZ="27" angleY="180" scale="1" radius="1" respawnTime="1" msgId="npc0001"/>
	<spawn type="privateZone" engName="Tamama" code="19005441" teamId="1" spawnId="7" posX="23" posY="2" posZ="12" angleY="180" scale="1" radius="1" respawnTime="1" msgId="npc0001"/>
	<spawn type="privateZone" engName="Tamama" code="19005441" teamId="1" spawnId="8" posX="27" posY="0.5" posZ="-12" angleY="180" scale="1" radius="1" respawnTime="1" msgId="npc0001"/>
	<spawn type="privateZone" engName="Tamama" code="19005441" teamId="1" spawnId="9" posX="23" posY="2" posZ="-19" angleY="180" scale="1" radius="1" respawnTime="1" msgId="npc0001"/>
	<spawn type="NONE_TYPE" engName="restoration_7" code="154140679" teamId="0" spawnId="10" posX="23" posY="2" posZ="37" angleY="180" scale="1" radius="1" respawnTime="1" msgId="npc0001"/>
	<spawn type="NONE_TYPE" engName="restoration_7" code="154140679" teamId="0" spawnId="11" posX="22" posY="2" posZ="37" angleY="180" scale="1" radius="1" respawnTime="1" msgId="npc0001"/>
	<spawn type="NONE_TYPE" engName="restoration_7" code="154140679" teamId="0" spawnId="12" posX="22" posY="2" posZ="38" angleY="180" scale="1" radius="1" respawnTime="1" msgId="npc0001"/>
	<spawn type="NONE_TYPE" engName="restoration_7" code="154140679" teamId="0" spawnId="13" posX="23" posY="2" posZ="38" angleY="180" scale="1" radius="1" respawnTime="1" msgId="npc0001"/>
	<spawn type="NONE_TYPE" engName="restoration_7" code="154140679" teamId="0" spawnId="14" posX="-24" posY="2" posZ="-36" angleY="180" scale="1" radius="1" respawnTime="1" msgId="npc0001"/>
	<spawn type="NONE_TYPE" engName="restoration_7" code="154140679" teamId="0" spawnId="15" posX="-23" posY="2" posZ="-36" angleY="180" scale="1" radius="1" respawnTime="1" msgId="npc0001"/>
	<spawn type="NONE_TYPE" engName="restoration_7" code="154140679" teamId="0" spawnId="16" posX="-23" posY="2" posZ="-37" angleY="180" scale="1" radius="1" respawnTime="1" msgId="npc0001"/>
	<spawn type="NONE_TYPE" engName="restoration_7" code="154140679" teamId="0" spawnId="17" posX="-24" posY="2" posZ="-37" angleY="180" scale="1" radius="1" respawnTime="1" msgId="npc0001"/>
</SPAWN.XML>
